phoneintel/DISCLAIMER.txt
phoneintel/LICENSE.txt
phoneintel/README.md
phoneintel/__init__.py
phoneintel/main.py
phoneintel/src/resources/countries/countries.csv
phoneintel/src/resources/countries/countries_langs.json
phoneintel/src/resources/countries/country_coordinates.json
phoneintel/src/resources/dorks/dorks.json
phoneintel/src/resources/user/init.txt
phoneintel/src/resources/user_agents/agents.txt
phoneintel/src/utils/__init__.py
phoneintel/src/utils/api_utils.py
phoneintel/src/utils/browser.py
phoneintel/src/utils/c_qui.py
phoneintel/src/utils/const.py
phoneintel/src/utils/credits.py
phoneintel/src/utils/dorking.py
phoneintel/src/utils/instagram.py
phoneintel/src/utils/internet.py
phoneintel/src/utils/map.py
phoneintel/src/utils/neutrino.py
phoneintel/src/utils/phone.py
phoneintel/src/utils/spamcalls.py
phoneintel/src/utils/tellows.py
phoneintel/src/utils/text.py
phoneintel-1.1.1.dist-info/LICENSE
phoneintel-1.1.1.dist-info/METADATA
phoneintel-1.1.1.dist-info/WHEEL
phoneintel-1.1.1.dist-info/entry_points.txt
phoneintel-1.1.1.dist-info/top_level.txt
phoneintel-1.1.1.dist-info/RECORD
